README.md
setup.py
geospacepy/__init__.py
geospacepy/array_management.py
geospacepy/omnireader.py
geospacepy/orbits.py
geospacepy/rotations.py
geospacepy/satplottools.py
geospacepy/special_datetime.py
geospacepy/spherical_geometry.py
geospacepy/sun.py
geospacepy/terrestrial_ellipsoidal.py
geospacepy/terrestrial_spherical.py
geospacepy.egg-info/PKG-INFO
geospacepy.egg-info/SOURCES.txt
geospacepy.egg-info/dependency_links.txt
geospacepy.egg-info/not-zip-safe
geospacepy.egg-info/requires.txt
geospacepy.egg-info/top_level.txt