Metadata-Version: 1.1
Name: geospacepy
Version: 0.2.2
Summary: A small library for geospace data analysis
Home-page: https://github.com/lkilcommons/geospacepy-lite
Author: Liam Kilcommons
Author-email: liam.kilcommons@colorado.edu
License: LICENSE.txt
Download-URL: https://github.com/lkilcommons/geospacepy-lite
Platform: UNKNOWN
Classifier: Development Status :: 4 - Beta
Classifier: Topic :: Scientific/Engineering
Classifier: Intended Audience :: Science/Research
Classifier: Natural Language :: English
Classifier: Programming Language :: Python
